wcfutils/__init__.py
wcfutils/__version__.py
wcfutils/core.py
wcfutils-0.1.12.dist-info/LICENSE
wcfutils-0.1.12.dist-info/METADATA
wcfutils-0.1.12.dist-info/WHEEL
wcfutils-0.1.12.dist-info/top_level.txt
wcfutils-0.1.12.dist-info/RECORD
