Metadata-Version: 2.1
Name: wcfutils
Version: 0.1.12
Summary: Handy utils written by 
Home-page: https://chenfei-wu.github.io/
Author: Chenfei Wu
Author-email: cqwuchenfei@163.com
License: MIT
Classifier: License :: OSI Approved :: Academic Free License (AFL)
Classifier: Programming Language :: Python
Classifier: Programming Language :: Python :: 3
Requires-Python: >=3.10
License-File: LICENSE
Requires-Dist: colorlog
Requires-Dist: redis
Requires-Dist: fsspec
Requires-Dist: boto3
Requires-Dist: tqdm
Requires-Dist: pyyaml
Requires-Dist: msgpack
Requires-Dist: Pillow
Requires-Dist: configobj
Requires-Dist: requests
Requires-Dist: psutil
Requires-Dist: imageio
Requires-Dist: h5py
Requires-Dist: json-lines
Requires-Dist: numpy
Requires-Dist: pandas
Requires-Dist: torch
Requires-Dist: torchvision
Requires-Dist: torchdata
Requires-Dist: einops
Requires-Dist: tensorboard
Requires-Dist: wandb
Requires-Dist: safetensors
Requires-Dist: opencv-python
Requires-Dist: av
Requires-Dist: webdataset
Requires-Dist: loguru
Requires-Dist: vaex
Requires-Dist: setuptools
